tensorgrad_lexer/__init__.py
tensorgrad_lexer/tensorgrad_lexer.py
tglexer-0.4.0.dist-info/LICENSE
tglexer-0.4.0.dist-info/METADATA
tglexer-0.4.0.dist-info/WHEEL
tglexer-0.4.0.dist-info/entry_points.txt
tglexer-0.4.0.dist-info/top_level.txt
tglexer-0.4.0.dist-info/RECORD
